refinery/__init__.py
refinery/explore.py
refinery/lib/__init__.py
refinery/lib/argformats.py
refinery/lib/argparser.py
refinery/lib/chunks.py
refinery/lib/crypto.py
refinery/lib/decorators.py
refinery/lib/deobfuscation.py
refinery/lib/frame.py
refinery/lib/java.py
refinery/lib/json.py
refinery/lib/loader.py
refinery/lib/magic.py
refinery/lib/meta.py
refinery/lib/mime.py
refinery/lib/mscrypto.py
refinery/lib/powershell.py
refinery/lib/structures.py
refinery/lib/suffixtree.py
refinery/lib/tools.py
refinery/lib/types.py
refinery/lib/xml.py
refinery/lib/dotnet/__init__.py
refinery/lib/dotnet/deserialize.py
refinery/lib/dotnet/header.py
refinery/lib/dotnet/resources.py
refinery/lib/dotnet/types.py
refinery/lib/patterns/__init__.py
refinery/lib/patterns/tlds.py
refinery/units/__init__.py
refinery/units/blockwise/__init__.py
refinery/units/blockwise/add.py
refinery/units/blockwise/bitrev.py
refinery/units/blockwise/blockop.py
refinery/units/blockwise/map.py
refinery/units/blockwise/neg.py
refinery/units/blockwise/pack.py
refinery/units/blockwise/rev.py
refinery/units/blockwise/rotl.py
refinery/units/blockwise/rotr.py
refinery/units/blockwise/shl.py
refinery/units/blockwise/shr.py
refinery/units/blockwise/sub.py
refinery/units/blockwise/terminate.py
refinery/units/blockwise/transpose.py
refinery/units/blockwise/xor.py
refinery/units/compression/__init__.py
refinery/units/compression/ap.py
refinery/units/compression/blz.py
refinery/units/compression/bz2.py
refinery/units/compression/decompress.py
refinery/units/compression/lz.py
refinery/units/compression/lz4.py
refinery/units/compression/lznt1.py
refinery/units/compression/zl.py
refinery/units/crypto/__init__.py
refinery/units/crypto/cipher/__init__.py
refinery/units/crypto/cipher/aes.py
refinery/units/crypto/cipher/blowfish.py
refinery/units/crypto/cipher/cast.py
refinery/units/crypto/cipher/chacha.py
refinery/units/crypto/cipher/des.py
refinery/units/crypto/cipher/des3.py
refinery/units/crypto/cipher/hc128.py
binary_refinery-0.3.36.dist-info/LICENSE
binary_refinery-0.3.36.dist-info/METADATA
binary_refinery-0.3.36.dist-info/WHEEL
binary_refinery-0.3.36.dist-info/entry_points.txt
binary_refinery-0.3.36.dist-info/top_level.txt
binary_refinery-0.3.36.dist-info/RECORD
