Metadata-Version: 2.1
Name: binary-refinery
Version: 0.3.36
Summary: A toolkit to transform and refine (mostly) binary data.
Home-page: https://github.com/binref/refinery/
Author: Jesko Hüttenhain
License: UNKNOWN
Platform: UNKNOWN
Classifier: Development Status :: 3 - Alpha
Classifier: Environment :: Console
Classifier: License :: OSI Approved :: BSD License
Classifier: Operating System :: OS Independent
Classifier: Programming Language :: Python :: 3 :: Only
Classifier: Topic :: System :: Shells
Classifier: Topic :: Utilities
Requires-Python: >=3.7
License-File: LICENSE
Requires-Dist: Pillow
Requires-Dist: acefile
Requires-Dist: asn1crypto
Requires-Dist: capstone
Requires-Dist: chardet
Requires-Dist: colorama
Requires-Dist: defusedxml
Requires-Dist: extract-msg
Requires-Dist: javaobj-py3 (>=0.4.0.1)
Requires-Dist: jsbeautifier
Requires-Dist: macholib
Requires-Dist: msgpack
Requires-Dist: msoffcrypto-tool
Requires-Dist: numpy (==1.19.3)
Requires-Dist: olefile
Requires-Dist: oletools
Requires-Dist: openpyxl
Requires-Dist: pefile
Requires-Dist: phpserialize
Requires-Dist: py7zr
Requires-Dist: pycdlib
Requires-Dist: pycryptodome
Requires-Dist: pyelftools
Requires-Dist: pyperclip
Requires-Dist: python-magic
Requires-Dist: python-registry
Requires-Dist: xlrd2
